README.md
setup.py
ProxyMan/__init__.py
ProxyMan/proxyman.py
ProxyMan.egg-info/PKG-INFO
ProxyMan.egg-info/SOURCES.txt
ProxyMan.egg-info/dependency_links.txt
ProxyMan.egg-info/requires.txt
ProxyMan.egg-info/top_level.txt